gff_tpg_pack/.python-version
gff_tpg_pack/__init__.py
gff_tpg_pack/annotation.py
gff_tpg_pack/gene_uniprot_interop/README.md
gff_tpg_pack/gene_uniprot_interop/assets/indice.jpg
gff_tpg_pack/gene_uniprot_interop/data/proteins_uniprot.txt.gz
gff_tpg_pack/gene_uniprot_interop/data/countings/countings1.tsv
gff_tpg_pack/gene_uniprot_interop/data/countings/countings2.tsv
gff_tpg_pack/gene_uniprot_interop/data/countings/countings3.tsv
gff_tpg_pack/gene_uniprot_interop/data/countings/countings4.tsv
gff_tpg_pack/gene_uniprot_interop/data/countings/countings5.tsv
gff_tpg_pack/gene_uniprot_interop/data/genes_annotations/annotation.gff
gff_tpg_pack-0.1.1.dist-info/METADATA
gff_tpg_pack-0.1.1.dist-info/WHEEL
gff_tpg_pack-0.1.1.dist-info/entry_points.txt
gff_tpg_pack-0.1.1.dist-info/RECORD
