Metadata-Version: 2.3
Name: gff-tpg-pack
Version: 0.1.1
Summary: Analyses des données d'annotation GFF
Project-URL: repo_git, http://pedago-service.univ-lyon1.fr:2325/tgagnieu/xomics/-/tree/publish?ref_type=heads
Author-email: Thomas Gagnieu <thomas.gagnieu@etu.univ-lyon1.fr>, Paul Gilbert <paul.gilbert@etu.univ-lyon1.fr>
Maintainer-email: Thomas Gagnieu <thomas.gagnieu@etu.univ-lyon1.fr>, Paul Gilbert <paul.gilbert@etu.univ-lyon1.fr>
Keywords: annotation,exon,gene,gff,parser,transcript
Requires-Python: >=3.10
Requires-Dist: matplotlib>=3.9.2
